LICENSE.txt
MANIFEST.in
README.rst
setup.py
djangolytics/__init__.py
djangolytics/models.py
djangolytics/urls.py
djangolytics/views.py
djangolytics_client.egg-info/PKG-INFO
djangolytics_client.egg-info/SOURCES.txt
djangolytics_client.egg-info/dependency_links.txt
djangolytics_client.egg-info/not-zip-safe
djangolytics_client.egg-info/top_level.txt
docs/Makefile
docs/conf.py
docs/index.rst
docs/make.bat